file_converter/__init__.py
file_converter/__main__.py
file_converter/convert.py
guryansh_textconverter-1.0.4.dist-info/LICENSE
guryansh_textconverter-1.0.4.dist-info/METADATA
guryansh_textconverter-1.0.4.dist-info/WHEEL
guryansh_textconverter-1.0.4.dist-info/entry_points.txt
guryansh_textconverter-1.0.4.dist-info/top_level.txt
guryansh_textconverter-1.0.4.dist-info/RECORD
