Metadata-Version: 2.1
Name: guryansh-textconverter
Version: 1.0.4
Summary: Python package for Square
Author: Guryansh
Author-email: guryanshsingla@gmail.com
License: MIT
Classifier: License :: OSI Approved :: MIT License
Classifier: Programming Language :: Python :: 3
Classifier: Programming Language :: Python :: 3.6
Classifier: Programming Language :: Python :: 3.7
Classifier: Programming Language :: Python :: 3.8
Classifier: Programming Language :: Python :: 3.9
License-File: LICENSE
Requires-Dist: argparse
